pathbridge/__init__.py
pathbridge/py.typed
pathbridge-0.0.0.dist-info/METADATA
pathbridge-0.0.0.dist-info/WHEEL
pathbridge-0.0.0.dist-info/licenses/LICENSE
pathbridge-0.0.0.dist-info/RECORD
