Metadata-Version: 2.4
Name: pathbridge
Version: 0.0.0
Summary: Translate validator error locations back to your application's schema paths and emit structured errors
Project-URL: Homepage, https://github.com/pilosus/pathbridge
Project-URL: Repository, https://github.com/pilosus/pathbridge
Project-URL: Issues, https://github.com/pilosus/pathbridge/issues
Author-email: Vitaly Samigullin <vrs@pilosus.org>
License-Expression: MIT
License-File: LICENSE
Classifier: Development Status :: 3 - Alpha
Classifier: Intended Audience :: Developers
Classifier: License :: OSI Approved :: MIT License
Classifier: Operating System :: OS Independent
Classifier: Programming Language :: Python :: 3
Classifier: Programming Language :: Python :: 3.10
Classifier: Programming Language :: Python :: 3.11
Classifier: Programming Language :: Python :: 3.12
Classifier: Programming Language :: Python :: 3.13
Classifier: Programming Language :: Python :: 3.14
Classifier: Typing :: Typed
Requires-Python: >=3.10
Provides-Extra: dev
Requires-Dist: mypy>=1.0; extra == 'dev'
Requires-Dist: pytest-cov>=4.0; extra == 'dev'
Requires-Dist: pytest>=8.0; extra == 'dev'
Requires-Dist: ruff>=0.4; extra == 'dev'
